vengeance/__init__.py
vengeance/conditional.py
vengeance/version.py
vengeance/classes/__init__.py
vengeance/classes/flux_cls.py
vengeance/classes/flux_row_cls.py
vengeance/classes/log_cls.py
vengeance/excel_com/__init__.py
vengeance/excel_com/excel_address.py
vengeance/excel_com/excel_constants.py
vengeance/excel_com/workbook.py
vengeance/excel_com/worksheet.py
vengeance/excel_com/classes/__init__.py
vengeance/excel_com/classes/excel_levity_cls.py
vengeance/excel_com/classes/lev_cls.py
vengeance/excel_com/classes/lev_row_cls.py
vengeance/util/__init__.py
vengeance/util/dates.py
vengeance/util/filesystem.py
vengeance/util/iter.py
vengeance/util/text.py
vengeance/util/classes/__init__.py
vengeance/util/classes/namespace_cls.py
vengeance/util/classes/parsed_time_cls.py
vengeance/util/classes/tree_cls.py
vengeance-1.1.38.dist-info/LICENSE
vengeance-1.1.38.dist-info/METADATA
vengeance-1.1.38.dist-info/WHEEL
vengeance-1.1.38.dist-info/top_level.txt
vengeance-1.1.38.dist-info/RECORD
