Metadata-Version: 2.1
Name: vengeance
Version: 1.1.38
Summary: Data Subjugation library for row-major organization of tabular data and control over the Excel Application
Home-page: https://github.com/michael-ross-ven/vengeance
Author: Michael Ross
Author-email: 
License: MIT
Classifier: Programming Language :: Python :: 3
Classifier: License :: OSI Approved :: MIT License
License-File: LICENSE
Requires-Dist: comtypes
Requires-Dist: pypiwin32
Requires-Dist: python-dateutil ; python_version>='3.0'
Requires-Dist: numpy ; python_version>='3.0'
